LICENSE.md
MANIFEST.in
README.md
requirements.txt
screenshot-1.jpg
setup.cfg
setup.py
vy
vy.png
vy.egg-info/PKG-INFO
vy.egg-info/SOURCES.txt
vy.egg-info/dependency_links.txt
vy.egg-info/top_level.txt
vyapp/__init__.py
vyapp/app.py
vyapp/areavi.py
vyapp/ask.py
vyapp/base.py
vyapp/completion.py
vyapp/dap.py
vyapp/mixins.py
vyapp/notebook.py
vyapp/panel.py
vyapp/regutils.py
vyapp/statusbar.py
vyapp/stderr.py
vyapp/stdout.py
vyapp/tools.py
vyapp/vyrc
vyapp/widgets.py
vyapp/plugins/__init__.py
vyapp/plugins/assoc.py
vyapp/plugins/blink_pair.py
vyapp/plugins/block_sel.py
vyapp/plugins/builtin_modes.py
vyapp/plugins/c_mode.py
vyapp/plugins/caps.py
vyapp/plugins/clip_path.py
vyapp/plugins/clipboard.py
vyapp/plugins/cmd.py
vyapp/plugins/cmd_search.py
vyapp/plugins/cmd_utils.py
vyapp/plugins/codec.py
vyapp/plugins/count_words.py
vyapp/plugins/cplusplus_mode.py
vyapp/plugins/cursor_status.py
vyapp/plugins/data_del.py
vyapp/plugins/data_sel.py
vyapp/plugins/deadcode.py
vyapp/plugins/delve.py
vyapp/plugins/editrc.py
vyapp/plugins/find.py
vyapp/plugins/fsearch.py
vyapp/plugins/fsniffer.py
vyapp/plugins/fstmt.py
vyapp/plugins/gdb.py
vyapp/plugins/gists.py
vyapp/plugins/gohints.py
vyapp/plugins/golang_mode.py
vyapp/plugins/hlink.py
vyapp/plugins/home.py
vyapp/plugins/html_mode.py
vyapp/plugins/ibash.py
vyapp/plugins/inline_comment.py
vyapp/plugins/io.py
vyapp/plugins/io_status.py
vyapp/plugins/iocmd.py
vyapp/plugins/javascript_mode.py
vyapp/plugins/jedi.py
vyapp/plugins/jsdebugger.py
vyapp/plugins/jsonfmt.py
vyapp/plugins/line_feed.py
vyapp/plugins/line_index.py
vyapp/plugins/line_scroll.py
vyapp/plugins/line_strips.py
vyapp/plugins/main_jumps.py
vyapp/plugins/mc.py
vyapp/plugins/mode_shortcut.py
vyapp/plugins/mypy.py
vyapp/plugins/outputs.py
vyapp/plugins/page_scroll.py
vyapp/plugins/pair_sel.py
vyapp/plugins/pane_jumps.py
vyapp/plugins/pane_resize.py
vyapp/plugins/pdb.py
vyapp/plugins/plugin_tools.py
vyapp/plugins/project.py
vyapp/plugins/python_mode.py
vyapp/plugins/quick_jumps.py
vyapp/plugins/quick_search.py
vyapp/plugins/quick_sel.py
vyapp/plugins/range_sel.py
